cryptonow/__init__.py
cryptonow/test.py
cryptonow_persian-0.3.0.dist-info/METADATA
cryptonow_persian-0.3.0.dist-info/WHEEL
cryptonow_persian-0.3.0.dist-info/top_level.txt
cryptonow_persian-0.3.0.dist-info/RECORD
