Metadata-Version: 2.4
Name: cryptonow-persian
Version: 0.3.0
Summary: Advanced crypto price getter with async, caching, Persian support
Author: SHAYAN
Classifier: Programming Language :: Python :: 3
Classifier: License :: OSI Approved :: MIT License
Classifier: Operating System :: OS Independent
Requires-Python: >=3.7
Requires-Dist: httpx
